mcae/__init__.py
mcae/example.py
mcae/example1.py
mcae/function_generation.py
mcae/particle.py
mcae/points.py
mcae/setblock.py
mcae/visualization.py
mcae-0.1.1.dist-info/METADATA
mcae-0.1.1.dist-info/WHEEL
mcae-0.1.1.dist-info/top_level.txt
mcae-0.1.1.dist-info/RECORD
