Metadata-Version: 2.1
Name: mcae
Version: 0.1.1
Summary: 一个用于制作Minecraft原版指令动画的工具
Home-page: https://github.com/luoyily/mcae
Author: luoyily
Keywords: a Minecraft command animation tool
Classifier: Programming Language :: Python :: 3
Classifier: License :: OSI Approved :: MIT License
Classifier: Operating System :: OS Independent
Requires-Python: >=3.11
Requires-Dist: Pillow >=10.0.1
Requires-Dist: numpy >=1.26.0
Requires-Dist: matplotlib >=3.8.1
